{"version":1,"resource":"file:///home/abu/python-projects/interview/class_test.py","entries":[{"id":"yzzL.py","timestamp":1675506001039},{"id":"MfE8.py","timestamp":1675506031949},{"id":"srmP.py","timestamp":1675506057602},{"id":"89tI.py","timestamp":1675506083285},{"id":"2N9J.py","timestamp":1675506102565},{"id":"cpJj.py","timestamp":1675506114922},{"id":"WmP5.py","timestamp":1675506145809},{"id":"pRAs.py","source":"undoRedo.source","timestamp":1675506149289},{"id":"ulav.py","timestamp":1675506460325},{"id":"DXkf.py","timestamp":1675506486925},{"id":"vszL.py","timestamp":1675506514049},{"id":"XcnP.py","timestamp":1675506599432},{"id":"UqBh.py","timestamp":1675506615932},{"id":"MtvC.py","timestamp":1675506825005},{"id":"E5Wa.py","timestamp":1675506923512}]}